notte_eval/__init__.py
notte_eval/patcher.py
notte_eval/py.typed
notte_eval/run.py
notte_eval/task_types.py
notte_eval/agent_handlers/__init__.py
notte_eval/agent_handlers/falco.py
notte_eval/agent_handlers/mock.py
notte_eval/data/__init__.py
notte_eval/data/eval.py
notte_eval/data/load_data.py
notte_eval/data/gaia/GAIA_webvoyager.jsonl
notte_eval/data/scratch/proxy.jsonl
notte_eval/data/webvoyager/convert.py
notte_eval/data/webvoyager/webvoyager.jsonl
notte_eval/data/webvoyager/webvoyager_convergence.jsonl
notte_eval/data/webvoyager/webvoyager_excluded.jsonl
notte_eval/data/webvoyager/webvoyager_simple.jsonl
notte_eval/data/webvoyager/webvoyager_single.jsonl
notte_eval/data/webvoyager/archive/WebVoyager_data.jsonl
notte_eval/data/webvoyager/archive/WebVoyager_data_short.jsonl
notte_eval/data/webvoyager/archive/WebVoyager_data_simple.jsonl
notte_eval/data/webvoyager/archive/WebVoyager_data_single.jsonl
notte_eval/data/webvoyager/archive/webvoyager_excluded.jsonl
notte_eval/evaluators/__init__.py
notte_eval/evaluators/evaluator.py
notte_eval/evaluators/webvoyager.py
notte_eval/webvoyager/__init__.py
notte_eval/webvoyager/analysis.py
notte_eval/webvoyager/bench_types.py
notte_eval/webvoyager/conftest.py
notte_eval/webvoyager/run.py
notte_eval/webvoyager/test_run.py
notte_eval-1.8.3.dist-info/METADATA
notte_eval-1.8.3.dist-info/WHEEL
notte_eval-1.8.3.dist-info/RECORD
