Metadata-Version: 2.4
Name: notte-eval
Version: 1.8.3
Summary: The evaluation for Notte
Author-email: Notte Team  <hello@notte.cc>
Requires-Python: >=3.11
Requires-Dist: cloudpickle>=3.1.1
Requires-Dist: notte-agent==v1.8.3
Requires-Dist: notte-browser==v1.8.3
Requires-Dist: notte-core==v1.8.3
Requires-Dist: notte-integrations==v1.8.3
Requires-Dist: notte-llm==v1.8.3
Requires-Dist: notte-sdk==v1.8.3
Requires-Dist: pandas
Requires-Dist: pebble>=5.1.1
